ce_mkc.py
ce_mkc-0.1.0.dist-info/METADATA
ce_mkc-0.1.0.dist-info/WHEEL
ce_mkc-0.1.0.dist-info/RECORD
