Metadata-Version: 2.1
Name: ce-mkc
Version: 0.1.0
Summary: A command line utility to set up Kafka, MongoDB, and MongoDB Kafka Connector environments.
License: MIT
Author: Your Name
Author-email: you@example.com
Requires-Python: >=3.10,<3.11
Classifier: License :: OSI Approved :: MIT License
Classifier: Programming Language :: Python :: 3
Classifier: Programming Language :: Python :: 3.10
Requires-Dist: certifi (==2023.7.22)
Requires-Dist: charset-normalizer (==3.2.0)
Requires-Dist: confluent-kafka (==2.2.0)
Requires-Dist: dnspython (==2.3.0)
Requires-Dist: docker (==6.1.3)
Requires-Dist: idna (==3.4)
Requires-Dist: packaging (==23.1)
Requires-Dist: pymongo (==4.5.0)
Requires-Dist: requests (>=1.26.6)
Requires-Dist: urllib3 (==2.0.4)
Requires-Dist: websocket-client (==1.6.1)
